odoo8_addon_donation_recurring-8.0.0.1.0-py2.7-nspkg.pth
odoo8_addon_donation_recurring-8.0.0.1.0.dist-info/top_level.txt
odoo8_addon_donation_recurring-8.0.0.1.0.dist-info/WHEEL
odoo8_addon_donation_recurring-8.0.0.1.0.dist-info/RECORD
odoo8_addon_donation_recurring-8.0.0.1.0.dist-info/metadata.json
odoo8_addon_donation_recurring-8.0.0.1.0.dist-info/DESCRIPTION.rst
odoo8_addon_donation_recurring-8.0.0.1.0.dist-info/METADATA
odoo8_addon_donation_recurring-8.0.0.1.0.dist-info/namespace_packages.txt
odoo_addons/donation_recurring/__openerp__.py
odoo_addons/donation_recurring/donation_view.xml
odoo_addons/donation_recurring/__init__.py
odoo_addons/donation_recurring/README.rst
odoo_addons/donation_recurring/donation.py
odoo_addons/donation_recurring/donation_recurring_demo.xml
odoo_addons/donation_recurring/i18n/fr.po
odoo_addons/donation_recurring/i18n/donation_recurring.pot
odoo_addons/donation_recurring/wizard/donation_recurring_generate.py
odoo_addons/donation_recurring/wizard/donation_recurring_generate_view.xml
odoo_addons/donation_recurring/wizard/__init__.py
odoo_addons/donation_recurring/test/generate_recurring_donations.yml
odoo_addons/donation_recurring/static/description/icon.png
